psycopg_dbconn_class/__init__.py
psycopg_dbconn_class/src/__init__.py
psycopg_dbconn_class/src/psycopg_dbconn_class.py
psycopg_dbconn_class-0.0.2.dist-info/LICENSE
psycopg_dbconn_class-0.0.2.dist-info/METADATA
psycopg_dbconn_class-0.0.2.dist-info/WHEEL
psycopg_dbconn_class-0.0.2.dist-info/top_level.txt
psycopg_dbconn_class-0.0.2.dist-info/RECORD
