Metadata-Version: 2.1
Name: psycopg-dbconn-class
Version: 0.0.2
Summary: A simple class to handle database connections using psycopg2 (PostgreSQL)
Home-page: https://github.com/kstenio/psycopg_dbconn_class
Author: Kleydson Stenio
Author-email: kleydson.stenio@gmail.com
Classifier: License :: OSI Approved :: GNU Lesser General Public License v3 (LGPLv3)
Classifier: Programming Language :: Python :: 3.9
Classifier: Operating System :: OS Independent
Requires-Python: >=3.9
License-File: LICENSE
Requires-Dist: psycopg2-binary ~=2.9.3
Provides-Extra: dev
Requires-Dist: twine >=4.0.2 ; extra == 'dev'
